{"cameraMode":{"drawMode":0,"name":"Shaded","section":"Shading Mode"},"sceneLighting":true,"audioPlay":false,"sceneViewState":{"m_AlwaysRefresh":false,"showFog":true,"showSkybox":true,"showFlares":true,"showImageEffects":true,"showParticleSystems":true,"showVisualEffectGraphs":true,"m_FxEnabled":true},"in2DMode":false,"pivot":{"x":178.09373474121095,"y":22.785232543945314,"z":-0.1126251220703125},"rotation":{"x":-0.4311772882938385,"y":0.008658366277813912,"z":-0.004146307706832886,"w":-0.9022403955459595},"size":642.0009155273438,"orthographic":false}